agentic_security/__init__.py
agentic_security/__main__.py
agentic_security/agents/__init__.py
agentic_security/agents/operator_crew.py
agentic_security/agents/operator_pydantic.py
agentic_security/app.py
agentic_security/config.py
agentic_security/core/app.py
agentic_security/core/logging.py
agentic_security/core/test_app.py
agentic_security/dependencies.py
agentic_security/http_spec.py
agentic_security/integrations/__init__.py
agentic_security/lib.py
agentic_security/logutils.py
agentic_security/mcp/__init__.py
agentic_security/mcp/client.py
agentic_security/mcp/main.py
agentic_security/middleware/cors.py
agentic_security/middleware/logging.py
agentic_security/misc/__init__.py
agentic_security/misc/banner.py
agentic_security/primitives/__init__.py
agentic_security/primitives/models.py
agentic_security/probe_actor/__init__.py
agentic_security/probe_actor/__main__.py
agentic_security/probe_actor/cost_module.py
agentic_security/probe_actor/fuzzer.py
agentic_security/probe_actor/operator.py
agentic_security/probe_actor/refusal.py
agentic_security/probe_actor/state.py
agentic_security/probe_data/__init__.py
agentic_security/probe_data/audio_generator.py
agentic_security/probe_data/data.py
agentic_security/probe_data/image_generator.py
agentic_security/probe_data/models.py
agentic_security/probe_data/modules/__init__.py
agentic_security/probe_data/modules/adaptive_attacks.py
agentic_security/probe_data/modules/fine_tuned.py
agentic_security/probe_data/modules/garak_tool.py
agentic_security/probe_data/modules/inspect_ai_tool.py
agentic_security/probe_data/modules/rl_model.py
agentic_security/probe_data/modules/test_adaptive_attacks.py
agentic_security/probe_data/modules/test_fine_tuned.py
agentic_security/probe_data/modules/test_rl_model.py
agentic_security/probe_data/msj_data.py
agentic_security/probe_data/stenography_fn.py
agentic_security/probe_data/test_audio_generator.py
agentic_security/probe_data/test_data.py
agentic_security/probe_data/test_image_generator.py
mseep_agentic_security-0.7.4.dist-info/LICENSE
mseep_agentic_security-0.7.4.dist-info/METADATA
mseep_agentic_security-0.7.4.dist-info/WHEEL
mseep_agentic_security-0.7.4.dist-info/entry_points.txt
mseep_agentic_security-0.7.4.dist-info/RECORD
