Metadata-Version: 2.3
Name: mseep-agentic_security
Version: 0.7.4
Summary: Agentic LLM vulnerability scanner
License: Apache-2.0
Keywords: LLM vulnerability scanner,llm security,llm adversarial attacks,prompt injection,prompt leakage,prompt injection attacks,prompt leakage prevention,llm vulnerabilities,owasp-llm-top-10
Author: mseep
Author-email: support@skydeck.ai
Maintainer: mseep
Maintainer-email: support@skydeck.ai
Requires-Python: >=3.11,<4.0
Classifier: License :: OSI Approved :: Apache Software License
Classifier: Programming Language :: Python :: 3
Classifier: Programming Language :: Python :: 3.11
Classifier: Programming Language :: Python :: 3.12
Classifier: Programming Language :: Python :: 3.13
Requires-Dist: cache-to-disk (>=2.0.0,<3.0.0)
Requires-Dist: colorama (>=0.4.4,<0.5.0)
Requires-Dist: datasets (>=3.3.0,<4.0.0)
Requires-Dist: fastapi (>=0.115.8,<0.116.0)
Requires-Dist: fire (==0.7.0)
Requires-Dist: gTTS (>=2.5.4,<3.0.0)
Requires-Dist: httpx (>=0.28.1,<0.29.0)
Requires-Dist: jinja2 (>=3.1.4,<4.0.0)
Requires-Dist: loguru (>=0.7.3,<0.8.0)
Requires-Dist: matplotlib (>=3.9.2,<4.0.0)
Requires-Dist: mcp (>=1.4.1,<2.0.0)
Requires-Dist: numpy (>=1.24.3,<3.0.0)
Requires-Dist: orjson (>=3.10,<4.0)
Requires-Dist: pandas (>=1.4,<3.0)
Requires-Dist: pydantic (==2.10.6)
Requires-Dist: pyfiglet (>=1.0.2,<2.0.0)
Requires-Dist: pytest-xdist (==3.6.1)
Requires-Dist: python-multipart (>=0.0.20,<0.0.21)
Requires-Dist: rich (==13.9.4)
Requires-Dist: scikit-learn (==1.6.1)
Requires-Dist: scikit-optimize (>=0.10.2,<0.11.0)
Requires-Dist: sentry_sdk (>=2.22.0,<3.0.0)
Requires-Dist: tabulate (>=0.8.9,<0.10.0)
Requires-Dist: termcolor (>=2.4.0,<3.0.0)
Requires-Dist: tomli (>=2.2.1,<3.0.0)
Requires-Dist: uvicorn (>=0.34.0,<0.35.0)
Project-URL: Documentation, https://github.com/msoedov/agentic_security/blob/main/README.md
Project-URL: Homepage, https://github.com/msoedov/agentic_security
Project-URL: Repository, https://github.com/msoedov/agentic_security
